scprep/__init__.py
scprep/_lazyload.py
scprep/_patch.py
scprep/filter.py
scprep/measure.py
scprep/normalize.py
scprep/reduce.py
scprep/sanitize.py
scprep/select.py
scprep/stats.py
scprep/transform.py
scprep/utils.py
scprep/version.py
scprep/io/__init__.py
scprep/io/csv.py
scprep/io/download.py
scprep/io/fcs.py
scprep/io/hdf5.py
scprep/io/mtx.py
scprep/io/tenx.py
scprep/io/utils.py
scprep/plot/__init__.py
scprep/plot/colors.py
scprep/plot/histogram.py
scprep/plot/jitter.py
scprep/plot/marker.py
scprep/plot/scatter.py
scprep/plot/scree.py
scprep/plot/tools.py
scprep/plot/utils.py
scprep/plot/variable_genes.py
scprep/run/__init__.py
scprep/run/conversion.py
scprep/run/dyngen.py
scprep/run/r_function.py
scprep/run/slingshot.py
scprep/run/splatter.py
scprep-1.2.3.dist-info/LICENSE
scprep-1.2.3.dist-info/METADATA
scprep-1.2.3.dist-info/WHEEL
scprep-1.2.3.dist-info/top_level.txt
scprep-1.2.3.dist-info/RECORD
