Metadata-Version: 2.1
Name: scprep
Version: 1.2.3
Summary: scprep
Home-page: https://github.com/KrishnaswamyLab/scprep
Download-URL: https://github.com/KrishnaswamyLab/scprep/archive/v1.2.3.tar.gz
Author: Scott Gigante, Daniel Burkhardt and Jay Stanley, Yale University
Author-email: krishnaswamylab@gmail.com
License: GNU General Public License Version 3
Keywords: big-data,computational-biology
Classifier: Development Status :: 4 - Beta
Classifier: Environment :: Console
Classifier: Framework :: Jupyter
Classifier: Intended Audience :: Developers
Classifier: Intended Audience :: Science/Research
Classifier: Natural Language :: English
Classifier: Operating System :: MacOS :: MacOS X
Classifier: Operating System :: Microsoft :: Windows
Classifier: Operating System :: POSIX :: Linux
Classifier: Programming Language :: Python :: 3
Classifier: Programming Language :: Python :: 3.6
Classifier: Programming Language :: Python :: 3.7
Classifier: Programming Language :: Python :: 3.8
Classifier: Programming Language :: Python :: 3.9
Classifier: Topic :: Scientific/Engineering :: Bio-Informatics
Requires-Python: >=3.6
License-File: LICENSE
Requires-Dist: numpy (>=1.12.0)
Requires-Dist: scipy (>=0.18.1)
Requires-Dist: scikit-learn (>=0.19.1)
Requires-Dist: decorator (>=4.3.0)
Requires-Dist: pandas (<2.1,>=0.25)
Requires-Dist: packaging
Provides-Extra: doc
Requires-Dist: sphinx (<2.4,>=2.2) ; extra == 'doc'
Requires-Dist: sphinxcontrib-napoleon ; extra == 'doc'
Requires-Dist: ipykernel ; extra == 'doc'
Requires-Dist: nbsphinx ; extra == 'doc'
Requires-Dist: autodocsumm ; extra == 'doc'
Provides-Extra: optional
Requires-Dist: fcsparser (<0.2.5) ; extra == 'optional'
Requires-Dist: tables ; extra == 'optional'
Requires-Dist: h5py ; extra == 'optional'
Requires-Dist: anndata ; extra == 'optional'
Requires-Dist: anndata2ri (>=1.0.6) ; extra == 'optional'
Provides-Extra: test
Requires-Dist: nose ; extra == 'test'
Requires-Dist: nose2 ; extra == 'test'
Requires-Dist: coverage ; extra == 'test'
Requires-Dist: coveralls ; extra == 'test'
Requires-Dist: parameterized ; extra == 'test'
Requires-Dist: requests ; extra == 'test'
Requires-Dist: packaging ; extra == 'test'
Requires-Dist: mock ; extra == 'test'
Requires-Dist: h5py ; extra == 'test'
Requires-Dist: matplotlib (>=3.0) ; extra == 'test'
Requires-Dist: rpy2 (>=3.4.3) ; extra == 'test'
Requires-Dist: black ; extra == 'test'
Requires-Dist: fcsparser (<0.2.5) ; extra == 'test'
Requires-Dist: tables ; extra == 'test'
Requires-Dist: anndata ; extra == 'test'
Requires-Dist: anndata2ri (>=1.0.6) ; extra == 'test'
